MANIFEST.in
README.md
requirements.txt
setup.cfg
setup.py
radiometric_normalization/__init__.py
radiometric_normalization/display.py
radiometric_normalization/filtering.py
radiometric_normalization/gimage.py
radiometric_normalization/normalize.py
radiometric_normalization/pca_filter.py
radiometric_normalization/pif.py
radiometric_normalization/robust.py
radiometric_normalization/time_stack.py
radiometric_normalization/transformation.py
radiometric_normalization/utils.py
radiometric_normalization/validation.py
radiometric_normalization.egg-info/PKG-INFO
radiometric_normalization.egg-info/SOURCES.txt
radiometric_normalization.egg-info/dependency_links.txt
radiometric_normalization.egg-info/requires.txt
radiometric_normalization.egg-info/top_level.txt