Metadata-Version: 1.1
Name: radiometric-normalization
Version: 0.1.168
Summary: Radiometric Normalization
Home-page: https://github.com/planetlabs/radiometric_normalization
Author: Arin Jumpasut
Author-email: arin.jumpasut@planet.com
License: UNKNOWN
Platform: UNKNOWN
Classifier: Development Status :: 1 - Planning
Classifier: License :: OSI Approved :: Apache Software License
Classifier: Programming Language :: Python :: 2.7
Classifier: Intended Audience :: Developers
Classifier: Intended Audience :: Information Technology
Classifier: Intended Audience :: Science/Research
Classifier: Topic :: Multimedia :: Graphics :: Graphics Conversion
Classifier: Topic :: Scientific/Engineering :: GIS
